[
    {
        "date": "2025-09-27",
        "symbol": "GO",
        "reportedCurrency": "USD",
        "cik": "0001771515",
        "fillingDate": "2025-11-05",
        "acceptedDate": "2025-11-05 16:07:33",
        "calendarYear": "2025",
        "period": "Q3",
        "cashAndCashEquivalents": 52125000,
        "shortTermInvestments": 0,
        "cashAndShortTermInvestments": 52125000,
        "netReceivables": 19152000,
        "inventory": 417846000,
        "otherCurrentAssets": 28335000,
        "totalCurrentAssets": 517458000,
        "propertyPlantEquipmentNet": 1941915000,
        "goodwill": 782835000,
        "intangibleAssets": 80098000,
        "goodwillAndIntangibleAssets": 862933000,
        "longTermInvestments": 41207000,
        "taxAssets": 0,
        "otherNonCurrentAssets": 5125000,
        "totalNonCurrentAssets": 2851180000,
        "otherAssets": 0,
        "totalAssets": 3368638000,
        "accountPayables": 196723000,
        "shortTermDebt": 99218000,
        "taxPayables": 12848000,
        "deferredRevenue": 0,
        "otherCurrentLiabilities": 89905000,
        "totalCurrentLiabilities": 398694000,
        "longTermDebt": 1712181000,
        "deferredRevenueNonCurrent": 0,
        "deferredTaxLiabilitiesNonCurrent": 56595000,
        "otherNonCurrentLiabilities": 2561000,
        "totalNonCurrentLiabilities": 1771337000,
        "otherLiabilities": 0,
        "capitalLeaseObligations": 1230632000,
        "totalLiabilities": 2170031000,
        "preferredStock": 0,
        "commonStock": 98000,
        "retainedEarnings": 374678000,
        "accumulatedOtherComprehensiveIncomeLoss": 0,
        "othertotalStockholdersEquity": 823831000,
        "totalStockholdersEquity": 1198607000,
        "totalEquity": 1198607000,
        "totalLiabilitiesAndStockholdersEquity": 3368638000,
        "minorityInterest": 0,
        "totalLiabilitiesAndTotalEquity": 3368638000,
        "totalInvestments": 41207000,
        "totalDebt": 1811399000,
        "netDebt": 1759274000,
        "link": "https://www.sec.gov/Archives/edgar/data/1771515/000177151525000169/0001771515-25-000169-index.htm",
        "finalLink": "https://www.sec.gov/Archives/edgar/data/1771515/000177151525000169/go-20250927.htm"
    },
    {
        "date": "2025-06-28",
        "symbol": "GO",
        "reportedCurrency": "USD",
        "cik": "0001771515",
        "fillingDate": "2025-08-06",
        "acceptedDate": "2025-08-06 16:06:37",
        "calendarYear": "2025",
        "period": "Q2",
        "cashAndCashEquivalents": 55190000,
        "shortTermInvestments": 0,
        "cashAndShortTermInvestments": 55190000,
        "netReceivables": 20723000,
        "inventory": 398225000,
        "otherCurrentAssets": 27397000,
        "totalCurrentAssets": 501535000,
        "propertyPlantEquipmentNet": 1912159000,
        "goodwill": 782835000,
        "intangibleAssets": 80681000,
        "goodwillAndIntangibleAssets": 863516000,
        "longTermInvestments": 39603000,
        "taxAssets": 0,
        "otherNonCurrentAssets": 5563000,
        "totalNonCurrentAssets": 2820841000,
        "otherAssets": 0,
        "totalAssets": 3322376000,
        "accountPayables": 211949000,
        "shortTermDebt": 95327000,
        "taxPayables": 9518000,
        "deferredRevenue": 0,
        "otherCurrentLiabilities": 98194000,
        "totalCurrentLiabilities": 414988000,
        "longTermDebt": 1666717000,
        "deferredRevenueNonCurrent": 0,
        "deferredTaxLiabilitiesNonCurrent": 51485000,
        "otherNonCurrentLiabilities": 2344000,
        "totalNonCurrentLiabilities": 1720546000,
        "otherLiabilities": 0,
        "capitalLeaseObligations": 1288094000,
        "totalLiabilities": 2135534000,
        "preferredStock": 0,
        "commonStock": 98000,
        "retainedEarnings": 363073000,
        "accumulatedOtherComprehensiveIncomeLoss": 0,
        "othertotalStockholdersEquity": 823671000,
        "totalStockholdersEquity": 1186842000,
        "totalEquity": 1186842000,
        "totalLiabilitiesAndStockholdersEquity": 3322376000,
        "minorityInterest": 0,
        "totalLiabilitiesAndTotalEquity": 3322376000,
        "totalInvestments": 39603000,
        "totalDebt": 1762044000,
        "netDebt": 1706854000,
        "link": "https://www.sec.gov/Archives/edgar/data/1771515/000177151525000141/0001771515-25-000141-index.htm",
        "finalLink": "https://www.sec.gov/Archives/edgar/data/1771515/000177151525000141/go-20250628.htm"
    },
    {
        "date": "2025-03-29",
        "symbol": "GO",
        "reportedCurrency": "USD",
        "cik": "0001771515",
        "fillingDate": "2025-05-07",
        "acceptedDate": "2025-05-07 16:03:47",
        "calendarYear": "2025",
        "period": "Q1",
        "cashAndCashEquivalents": 50910000,
        "shortTermInvestments": 0,
        "cashAndShortTermInvestments": 50910000,
        "netReceivables": 21306000,
        "inventory": 386170000,
        "otherCurrentAssets": 26524000,
        "totalCurrentAssets": 484910000,
        "propertyPlantEquipmentNet": 1879529000,
        "goodwill": 782835000,
        "intangibleAssets": 79951000,
        "goodwillAndIntangibleAssets": 862786000,
        "longTermInvestments": 38094000,
        "taxAssets": 0,
        "otherNonCurrentAssets": 6118000,
        "totalNonCurrentAssets": 2786527000,
        "otherAssets": 0,
        "totalAssets": 3271437000,
        "accountPayables": 193826000,
        "shortTermDebt": 90854000,
        "taxPayables": 10909000,
        "deferredRevenue": 0,
        "otherCurrentLiabilities": 93104000,
        "totalCurrentLiabilities": 388693000,
        "longTermDebt": 1650471000,
        "deferredRevenueNonCurrent": 0,
        "deferredTaxLiabilitiesNonCurrent": 50350000,
        "otherNonCurrentLiabilities": 2344000,
        "totalNonCurrentLiabilities": 1703165000,
        "otherLiabilities": 0,
        "capitalLeaseObligations": 1265599000,
        "totalLiabilities": 2091858000,
        "preferredStock": 0,
        "commonStock": 98000,
        "retainedEarnings": 358112000,
        "accumulatedOtherComprehensiveIncomeLoss": 0,
        "othertotalStockholdersEquity": 821369000,
        "totalStockholdersEquity": 1179579000,
        "totalEquity": 1179579000,
        "totalLiabilitiesAndStockholdersEquity": 3271437000,
        "minorityInterest": 0,
        "totalLiabilitiesAndTotalEquity": 3271437000,
        "totalInvestments": 38094000,
        "totalDebt": 1741325000,
        "netDebt": 1690415000,
        "link": "https://www.sec.gov/Archives/edgar/data/1771515/000177151525000090/0001771515-25-000090-index.htm",
        "finalLink": "https://www.sec.gov/Archives/edgar/data/1771515/000177151525000090/go-20250329.htm"
    },
    {
        "date": "2024-12-31",
        "symbol": "GO",
        "reportedCurrency": "USD",
        "cik": "0001771515",
        "fillingDate": "2025-02-26",
        "acceptedDate": "2025-02-26 16:03:32",
        "calendarYear": "2024",
        "period": "Q4",
        "cashAndCashEquivalents": 62828000,
        "shortTermInvestments": 0,
        "cashAndShortTermInvestments": 62828000,
        "netReceivables": 20217000,
        "inventory": 394152000,
        "otherCurrentAssets": 26701000,
        "totalCurrentAssets": 503898000,
        "propertyPlantEquipmentNet": 1765101000,
        "goodwill": 782734000,
        "intangibleAssets": 78778000,
        "goodwillAndIntangibleAssets": 861512000,
        "longTermInvestments": 36441000,
        "taxAssets": 0,
        "otherNonCurrentAssets": 6869000,
        "totalNonCurrentAssets": 2669923000,
        "otherAssets": 0,
        "totalAssets": 3173821000,
        "accountPayables": 175871000,
        "shortTermDebt": 87905000,
        "taxPayables": 10921000,
        "deferredRevenue": 0,
        "otherCurrentLiabilities": 74927000,
        "totalCurrentLiabilities": 349624000,
        "longTermDebt": 1568721000,
        "deferredRevenueNonCurrent": 0,
        "deferredTaxLiabilitiesNonCurrent": 56178000,
        "otherNonCurrentLiabilities": 1914000,
        "totalNonCurrentLiabilities": 1626813000,
        "otherLiabilities": 0,
        "capitalLeaseObligations": 1179124000,
        "totalLiabilities": 1976437000,
        "preferredStock": 0,
        "commonStock": 97000,
        "retainedEarnings": 381429000,
        "accumulatedOtherComprehensiveIncomeLoss": 0,
        "othertotalStockholdersEquity": 815858000,
        "totalStockholdersEquity": 1197384000,
        "totalEquity": 1197384000,
        "totalLiabilitiesAndStockholdersEquity": 3173821000,
        "minorityInterest": 0,
        "totalLiabilitiesAndTotalEquity": 3173821000,
        "totalInvestments": 36441000,
        "totalDebt": 1656626000,
        "netDebt": 1593798000,
        "link": "https://www.sec.gov/Archives/edgar/data/1771515/000177151525000017/0001771515-25-000017-index.htm",
        "finalLink": "https://www.sec.gov/Archives/edgar/data/1771515/000177151525000017/go-20241228.htm"
    },
    {
        "date": "2024-09-28",
        "symbol": "GO",
        "reportedCurrency": "USD",
        "cik": "0001771515",
        "fillingDate": "2024-11-06",
        "acceptedDate": "2024-11-06 16:09:19",
        "calendarYear": "2024",
        "period": "Q3",
        "cashAndCashEquivalents": 68653000,
        "shortTermInvestments": 0,
        "cashAndShortTermInvestments": 68653000,
        "netReceivables": 17775000,
        "inventory": 396893000,
        "otherCurrentAssets": 30651000,
        "totalCurrentAssets": 513972000,
        "propertyPlantEquipmentNet": 1728264000,
        "goodwill": 776585000,
        "intangibleAssets": 77256000,
        "goodwillAndIntangibleAssets": 853841000,
        "longTermInvestments": 32915999,
        "taxAssets": 0,
        "otherNonCurrentAssets": 9524000,
        "totalNonCurrentAssets": 2624545000,
        "otherAssets": 0,
        "totalAssets": 3138517000,
        "accountPayables": 197231000,
        "shortTermDebt": 76034000,
        "taxPayables": 11125000,
        "deferredRevenue": 0,
        "otherCurrentLiabilities": 67894000,
        "totalCurrentLiabilities": 352284000,
        "longTermDebt": 1505622000,
        "deferredRevenueNonCurrent": 0,
        "deferredTaxLiabilitiesNonCurrent": 52899000,
        "otherNonCurrentLiabilities": 1661000,
        "totalNonCurrentLiabilities": 1560182000,
        "otherLiabilities": 0,
        "capitalLeaseObligations": 1152377000,
        "totalLiabilities": 1912466000,
        "preferredStock": 0,
        "commonStock": 99000,
        "retainedEarnings": 379118000,
        "accumulatedOtherComprehensiveIncomeLoss": 0,
        "othertotalStockholdersEquity": 846834000,
        "totalStockholdersEquity": 1226051000,
        "totalEquity": 1226051000,
        "totalLiabilitiesAndStockholdersEquity": 3138517000,
        "minorityInterest": 0,
        "totalLiabilitiesAndTotalEquity": 3138517000,
        "totalInvestments": 32915999,
        "totalDebt": 1581656000,
        "netDebt": 1513003000,
        "link": "https://www.sec.gov/Archives/edgar/data/1771515/000177151524000150/0001771515-24-000150-index.htm",
        "finalLink": "https://www.sec.gov/Archives/edgar/data/1771515/000177151524000150/go-20240928.htm"
    },
    {
        "date": "2024-06-29",
        "symbol": "GO",
        "reportedCurrency": "USD",
        "cik": "0001771515",
        "fillingDate": "2024-08-07",
        "acceptedDate": "2024-08-07 16:03:48",
        "calendarYear": "2024",
        "period": "Q2",
        "cashAndCashEquivalents": 67065000,
        "shortTermInvestments": 0,
        "cashAndShortTermInvestments": 67065000,
        "netReceivables": 16631000,
        "inventory": 367313000,
        "otherCurrentAssets": 24259000,
        "totalCurrentAssets": 475268000,
        "propertyPlantEquipmentNet": 1711130000,
        "goodwill": 776832000,
        "intangibleAssets": 76887000,
        "goodwillAndIntangibleAssets": 853719000,
        "longTermInvestments": 30675000,
        "taxAssets": 0,
        "otherNonCurrentAssets": 9884000,
        "totalNonCurrentAssets": 2605408000,
        "otherAssets": 0,
        "totalAssets": 3080676000,
        "accountPayables": 210231000,
        "shortTermDebt": 77565000,
        "taxPayables": 7924000,
        "deferredRevenue": 0,
        "otherCurrentLiabilities": 72959000,
        "totalCurrentLiabilities": 368679000,
        "longTermDebt": 1448574000,
        "deferredRevenueNonCurrent": 0,
        "deferredTaxLiabilitiesNonCurrent": 41154000,
        "otherNonCurrentLiabilities": 1425000,
        "totalNonCurrentLiabilities": 1491153000,
        "otherLiabilities": 0,
        "capitalLeaseObligations": 1146959000,
        "totalLiabilities": 1859832000,
        "preferredStock": 0,
        "commonStock": 99000,
        "retainedEarnings": 354940000,
        "accumulatedOtherComprehensiveIncomeLoss": 0,
        "othertotalStockholdersEquity": 865805000,
        "totalStockholdersEquity": 1220844000,
        "totalEquity": 1220844000,
        "totalLiabilitiesAndStockholdersEquity": 3080676000,
        "minorityInterest": 0,
        "totalLiabilitiesAndTotalEquity": 3080676000,
        "totalInvestments": 30675000,
        "totalDebt": 1526139000,
        "netDebt": 1459074000,
        "link": "https://www.sec.gov/Archives/edgar/data/1771515/000177151524000130/0001771515-24-000130-index.htm",
        "finalLink": "https://www.sec.gov/Archives/edgar/data/1771515/000177151524000130/go-20240629.htm"
    },
    {
        "date": "2024-03-30",
        "symbol": "GO",
        "reportedCurrency": "USD",
        "cik": "0001771515",
        "fillingDate": "2024-05-08",
        "acceptedDate": "2024-05-08 16:05:17",
        "calendarYear": "2024",
        "period": "Q1",
        "cashAndCashEquivalents": 66885000,
        "shortTermInvestments": 0,
        "cashAndShortTermInvestments": 66885000,
        "netReceivables": 18831000,
        "inventory": 362730000,
        "otherCurrentAssets": 29954000,
        "totalCurrentAssets": 478400000,
        "propertyPlantEquipmentNet": 1629679000,
        "goodwill": 747943000,
        "intangibleAssets": 80189000,
        "goodwillAndIntangibleAssets": 828132000,
        "longTermInvestments": 28236000,
        "taxAssets": 0,
        "otherNonCurrentAssets": 10084000,
        "totalNonCurrentAssets": 2496131000,
        "otherAssets": 0,
        "totalAssets": 2974531000,
        "accountPayables": 223710000,
        "shortTermDebt": 69557000,
        "taxPayables": 14340000,
        "deferredRevenue": 0,
        "otherCurrentLiabilities": 74453000,
        "totalCurrentLiabilities": 382060000,
        "longTermDebt": 1329046000,
        "deferredRevenueNonCurrent": 0,
        "deferredTaxLiabilitiesNonCurrent": 36909000,
        "otherNonCurrentLiabilities": 1943000,
        "totalNonCurrentLiabilities": 1367898000,
        "otherLiabilities": 0,
        "capitalLeaseObligations": 1107647000,
        "totalLiabilities": 1749958000,
        "preferredStock": 0,
        "commonStock": 100000,
        "retainedEarnings": 340939000,
        "accumulatedOtherComprehensiveIncomeLoss": 0,
        "othertotalStockholdersEquity": 883534000,
        "totalStockholdersEquity": 1224573000,
        "totalEquity": 1224573000,
        "totalLiabilitiesAndStockholdersEquity": 2974531000,
        "minorityInterest": 0,
        "totalLiabilitiesAndTotalEquity": 2974531000,
        "totalInvestments": 28236000,
        "totalDebt": 1398603000,
        "netDebt": 1331718000,
        "link": "https://www.sec.gov/Archives/edgar/data/1771515/000177151524000094/0001771515-24-000094-index.htm",
        "finalLink": "https://www.sec.gov/Archives/edgar/data/1771515/000177151524000094/go-20240330.htm"
    },
    {
        "date": "2023-12-31",
        "symbol": "GO",
        "reportedCurrency": "USD",
        "cik": "0001771515",
        "fillingDate": "2024-02-28",
        "acceptedDate": "2024-02-28 16:01:24",
        "calendarYear": "2023",
        "period": "Q4",
        "cashAndCashEquivalents": 114987000,
        "shortTermInvestments": 0,
        "cashAndShortTermInvestments": 114987000,
        "netReceivables": 19128000,
        "inventory": 349993000,
        "otherCurrentAssets": 32443000,
        "totalCurrentAssets": 516551000,
        "propertyPlantEquipmentNet": 1588172000,
        "goodwill": 747943000,
        "intangibleAssets": 78556000,
        "goodwillAndIntangibleAssets": 826499000,
        "longTermInvestments": 28134000,
        "taxAssets": 0,
        "otherNonCurrentAssets": 10230000,
        "totalNonCurrentAssets": 2453035000,
        "otherAssets": 0,
        "totalAssets": 2969586000,
        "accountPayables": 209354000,
        "shortTermDebt": 69399000,
        "taxPayables": 13808000,
        "deferredRevenue": 0,
        "otherCurrentLiabilities": 91404000,
        "totalCurrentLiabilities": 383965000,
        "longTermDebt": 1325414000,
        "deferredRevenueNonCurrent": 0,
        "deferredTaxLiabilitiesNonCurrent": 38601000,
        "otherNonCurrentLiabilities": 2267000,
        "totalNonCurrentLiabilities": 1366282000,
        "otherLiabilities": 0,
        "capitalLeaseObligations": 1102081000,
        "totalLiabilities": 1750247000,
        "preferredStock": 0,
        "commonStock": 99000,
        "retainedEarnings": 341964000,
        "accumulatedOtherComprehensiveIncomeLoss": 0,
        "othertotalStockholdersEquity": 877276000,
        "totalStockholdersEquity": 1219339000,
        "totalEquity": 1219339000,
        "totalLiabilitiesAndStockholdersEquity": 2969586000,
        "minorityInterest": 0,
        "totalLiabilitiesAndTotalEquity": 2969586000,
        "totalInvestments": 28134000,
        "totalDebt": 1394813000,
        "netDebt": 1279826000,
        "link": "https://www.sec.gov/Archives/edgar/data/1771515/000177151524000016/0001771515-24-000016-index.htm",
        "finalLink": "https://www.sec.gov/Archives/edgar/data/1771515/000177151524000016/go-20231230.htm"
    },
    {
        "date": "2023-09-30",
        "symbol": "GO",
        "reportedCurrency": "USD",
        "cik": "0001771515",
        "fillingDate": "2023-11-08",
        "acceptedDate": "2023-11-08 16:01:19",
        "calendarYear": "2023",
        "period": "Q3",
        "cashAndCashEquivalents": 155663000,
        "shortTermInvestments": 0,
        "cashAndShortTermInvestments": 155663000,
        "netReceivables": 23145000,
        "inventory": 308605000,
        "otherCurrentAssets": 27076000,
        "totalCurrentAssets": 514489000,
        "propertyPlantEquipmentNet": 1553438000,
        "goodwill": 747943000,
        "intangibleAssets": 76958000,
        "goodwillAndIntangibleAssets": 824901000,
        "longTermInvestments": 25990000,
        "taxAssets": 0,
        "otherNonCurrentAssets": 10641000,
        "totalNonCurrentAssets": 2414970000,
        "otherAssets": 0,
        "totalAssets": 2929459000,
        "accountPayables": 183982000,
        "shortTermDebt": 68958000,
        "taxPayables": 14650000,
        "deferredRevenue": 0,
        "otherCurrentLiabilities": 116123000,
        "totalCurrentLiabilities": 383713000,
        "longTermDebt": 1305518000,
        "deferredRevenueNonCurrent": 0,
        "deferredTaxLiabilitiesNonCurrent": 35132000,
        "otherNonCurrentLiabilities": 2005000,
        "totalNonCurrentLiabilities": 1342655000,
        "otherLiabilities": 0,
        "capitalLeaseObligations": 1079967000,
        "totalLiabilities": 1726368000,
        "preferredStock": 0,
        "commonStock": 99000,
        "retainedEarnings": 327858000,
        "accumulatedOtherComprehensiveIncomeLoss": 0,
        "othertotalStockholdersEquity": 875134000,
        "totalStockholdersEquity": 1203091000,
        "totalEquity": 1203091000,
        "totalLiabilitiesAndStockholdersEquity": 2929459000,
        "minorityInterest": 0,
        "totalLiabilitiesAndTotalEquity": 2929459000,
        "totalInvestments": 25990000,
        "totalDebt": 1374476000,
        "netDebt": 1218813000,
        "link": "https://www.sec.gov/Archives/edgar/data/1771515/000177151523000103/0001771515-23-000103-index.htm",
        "finalLink": "https://www.sec.gov/Archives/edgar/data/1771515/000177151523000103/go-20230930.htm"
    },
    {
        "date": "2023-07-01",
        "symbol": "GO",
        "reportedCurrency": "USD",
        "cik": "0001771515",
        "fillingDate": "2023-08-09",
        "acceptedDate": "2023-08-09 16:03:00",
        "calendarYear": "2023",
        "period": "Q2",
        "cashAndCashEquivalents": 87570000,
        "shortTermInvestments": 0,
        "cashAndShortTermInvestments": 87570000,
        "netReceivables": 14448000,
        "inventory": 320344000,
        "otherCurrentAssets": 17930000,
        "totalCurrentAssets": 440292000,
        "propertyPlantEquipmentNet": 1525936000,
        "goodwill": 747943000,
        "intangibleAssets": 73084000,
        "goodwillAndIntangibleAssets": 821027000,
        "longTermInvestments": 0,
        "taxAssets": 0,
        "otherNonCurrentAssets": 35836000,
        "totalNonCurrentAssets": 2382799000,
        "otherAssets": 0,
        "totalAssets": 2823091000,
        "accountPayables": 147220000,
        "shortTermDebt": 66678000,
        "taxPayables": 11376000,
        "deferredRevenue": 0,
        "otherCurrentLiabilities": 95733000,
        "totalCurrentLiabilities": 321007000,
        "longTermDebt": 1305882000,
        "deferredRevenueNonCurrent": 0,
        "deferredTaxLiabilitiesNonCurrent": 29720000,
        "otherNonCurrentLiabilities": 1668000,
        "totalNonCurrentLiabilities": 1337270000,
        "otherLiabilities": 0,
        "capitalLeaseObligations": 1076275000,
        "totalLiabilities": 1658277000,
        "preferredStock": 0,
        "commonStock": 99000,
        "retainedEarnings": 300718000,
        "accumulatedOtherComprehensiveIncomeLoss": 0,
        "othertotalStockholdersEquity": 863997000,
        "totalStockholdersEquity": 1164814000,
        "totalEquity": 1164814000,
        "totalLiabilitiesAndStockholdersEquity": 2823091000,
        "minorityInterest": 0,
        "totalLiabilitiesAndTotalEquity": 2823091000,
        "totalInvestments": 0,
        "totalDebt": 1372560000,
        "netDebt": 1284990000,
        "link": "https://www.sec.gov/Archives/edgar/data/1771515/000177151523000087/0001771515-23-000087-index.htm",
        "finalLink": "https://www.sec.gov/Archives/edgar/data/1771515/000177151523000087/go-20230701.htm"
    },
    {
        "date": "2023-04-01",
        "symbol": "GO",
        "reportedCurrency": "USD",
        "cik": "0001771515",
        "fillingDate": "2023-05-10",
        "acceptedDate": "2023-05-10 16:11:10",
        "calendarYear": "2023",
        "period": "Q1",
        "cashAndCashEquivalents": 82115000,
        "shortTermInvestments": 0,
        "cashAndShortTermInvestments": 82115000,
        "netReceivables": 12970000,
        "inventory": 316397000,
        "otherCurrentAssets": 15725000,
        "totalCurrentAssets": 427207000,
        "propertyPlantEquipmentNet": 1491400000,
        "goodwill": 747943000,
        "intangibleAssets": 68713000,
        "goodwillAndIntangibleAssets": 816656000,
        "longTermInvestments": 0,
        "taxAssets": 0,
        "otherNonCurrentAssets": 34418000,
        "totalNonCurrentAssets": 2342474000,
        "otherAssets": 0,
        "totalAssets": 2769681000,
        "accountPayables": 158618000,
        "shortTermDebt": 64379000,
        "taxPayables": 9107000,
        "deferredRevenue": 0,
        "otherCurrentLiabilities": 68835000,
        "totalCurrentLiabilities": 300939000,
        "longTermDebt": 1313863000,
        "deferredRevenueNonCurrent": 0,
        "deferredTaxLiabilitiesNonCurrent": 25912000,
        "otherNonCurrentLiabilities": 1428000,
        "totalNonCurrentLiabilities": 1341203000,
        "otherLiabilities": 0,
        "capitalLeaseObligations": 1055181000,
        "totalLiabilities": 1642142000,
        "preferredStock": 0,
        "commonStock": 98000,
        "retainedEarnings": 276247000,
        "accumulatedOtherComprehensiveIncomeLoss": 0,
        "othertotalStockholdersEquity": 851194000,
        "totalStockholdersEquity": 1127539000,
        "totalEquity": 1127539000,
        "totalLiabilitiesAndStockholdersEquity": 2769681000,
        "minorityInterest": 0,
        "totalLiabilitiesAndTotalEquity": 2769681000,
        "totalInvestments": 0,
        "totalDebt": 1378242000,
        "netDebt": 1296127000,
        "link": "https://www.sec.gov/Archives/edgar/data/1771515/000177151523000048/0001771515-23-000048-index.htm",
        "finalLink": "https://www.sec.gov/Archives/edgar/data/1771515/000177151523000048/go-20230401.htm"
    },
    {
        "date": "2022-12-31",
        "symbol": "GO",
        "reportedCurrency": "USD",
        "cik": "0001771515",
        "fillingDate": "2023-03-01",
        "acceptedDate": "2023-03-01 16:12:56",
        "calendarYear": "2022",
        "period": "Q4",
        "cashAndCashEquivalents": 102728000,
        "shortTermInvestments": 0,
        "cashAndShortTermInvestments": 102728000,
        "netReceivables": 15173000,
        "inventory": 334319000,
        "otherCurrentAssets": 15137000,
        "totalCurrentAssets": 467357000,
        "propertyPlantEquipmentNet": 1462909000,
        "goodwill": 747943000,
        "intangibleAssets": 63993000,
        "goodwillAndIntangibleAssets": 811936000,
        "longTermInvestments": 0,
        "taxAssets": 0,
        "otherNonCurrentAssets": 30202000,
        "totalNonCurrentAssets": 2305047000,
        "otherAssets": 0,
        "totalAssets": 2772404000,
        "accountPayables": 137631000,
        "shortTermDebt": 54586000,
        "taxPayables": 7890000,
        "deferredRevenue": 0,
        "otherCurrentLiabilities": 80407000,
        "totalCurrentLiabilities": 280514000,
        "longTermDebt": 1360409000,
        "deferredRevenueNonCurrent": 0,
        "deferredTaxLiabilitiesNonCurrent": 19782000,
        "otherNonCurrentLiabilities": 1485000,
        "totalNonCurrentLiabilities": 1381676000,
        "otherLiabilities": 0,
        "capitalLeaseObligations": 1035345000,
        "totalLiabilities": 1662190000,
        "preferredStock": 0,
        "commonStock": 98000,
        "retainedEarnings": 262527000,
        "accumulatedOtherComprehensiveIncomeLoss": 0,
        "othertotalStockholdersEquity": 847589000,
        "totalStockholdersEquity": 1110214000,
        "totalEquity": 1110214000,
        "totalLiabilitiesAndStockholdersEquity": 2772404000,
        "minorityInterest": 0,
        "totalLiabilitiesAndTotalEquity": 2772404000,
        "totalInvestments": 0,
        "totalDebt": 1414995000,
        "netDebt": 1312267000,
        "link": "https://www.sec.gov/Archives/edgar/data/1771515/000177151523000009/0001771515-23-000009-index.htm",
        "finalLink": "https://www.sec.gov/Archives/edgar/data/1771515/000177151523000009/go-20221231.htm"
    },
    {
        "date": "2022-10-01",
        "symbol": "GO",
        "reportedCurrency": "USD",
        "cik": "0001771515",
        "fillingDate": "2022-11-09",
        "acceptedDate": "2022-11-09 16:05:13",
        "calendarYear": "2022",
        "period": "Q3",
        "cashAndCashEquivalents": 107277000,
        "shortTermInvestments": 0,
        "cashAndShortTermInvestments": 107277000,
        "netReceivables": 12223000,
        "inventory": 331891000,
        "otherCurrentAssets": 17186000,
        "totalCurrentAssets": 468577000,
        "propertyPlantEquipmentNet": 1444735000,
        "goodwill": 747943000,
        "intangibleAssets": 60676000,
        "goodwillAndIntangibleAssets": 808619000,
        "longTermInvestments": 0,
        "taxAssets": 0,
        "otherNonCurrentAssets": 29098000,
        "totalNonCurrentAssets": 2282452000,
        "otherAssets": 0,
        "totalAssets": 2751029000,
        "accountPayables": 143037000,
        "shortTermDebt": 55698000,
        "taxPayables": 8914000,
        "deferredRevenue": 0,
        "otherCurrentLiabilities": 79799000,
        "totalCurrentLiabilities": 287448000,
        "longTermDebt": 1361220000,
        "deferredRevenueNonCurrent": 0,
        "deferredTaxLiabilitiesNonCurrent": 17049000,
        "otherNonCurrentLiabilities": 0,
        "totalNonCurrentLiabilities": 1378269000,
        "otherLiabilities": 0,
        "capitalLeaseObligations": 1037657000,
        "totalLiabilities": 1665717000,
        "preferredStock": 0,
        "commonStock": 97000,
        "retainedEarnings": 246638000,
        "accumulatedOtherComprehensiveIncomeLoss": 0,
        "othertotalStockholdersEquity": 838577000,
        "totalStockholdersEquity": 1085312000,
        "totalEquity": 1085312000,
        "totalLiabilitiesAndStockholdersEquity": 2751029000,
        "minorityInterest": 0,
        "totalLiabilitiesAndTotalEquity": 2751029000,
        "totalInvestments": 0,
        "totalDebt": 1416918000,
        "netDebt": 1309641000,
        "link": "https://www.sec.gov/Archives/edgar/data/1771515/000177151522000151/0001771515-22-000151-index.htm",
        "finalLink": "https://www.sec.gov/Archives/edgar/data/1771515/000177151522000151/go-20221001.htm"
    },
    {
        "date": "2022-07-02",
        "symbol": "GO",
        "reportedCurrency": "USD",
        "cik": "0001771515",
        "fillingDate": "2022-08-10",
        "acceptedDate": "2022-08-10 16:06:35",
        "calendarYear": "2022",
        "period": "Q2",
        "cashAndCashEquivalents": 84260000,
        "shortTermInvestments": 0,
        "cashAndShortTermInvestments": 84260000,
        "netReceivables": 11818000,
        "inventory": 318424000,
        "otherCurrentAssets": 14532000,
        "totalCurrentAssets": 429034000,
        "propertyPlantEquipmentNet": 1430446000,
        "goodwill": 747943000,
        "intangibleAssets": 56789000,
        "goodwillAndIntangibleAssets": 804732000,
        "longTermInvestments": 0,
        "taxAssets": 0,
        "otherNonCurrentAssets": 29184000,
        "totalNonCurrentAssets": 2264362000,
        "otherAssets": 0,
        "totalAssets": 2693396000,
        "accountPayables": 132846000,
        "shortTermDebt": 50142000,
        "taxPayables": 6265000,
        "deferredRevenue": 0,
        "otherCurrentLiabilities": 71179000,
        "totalCurrentLiabilities": 260432000,
        "longTermDebt": 1361293000,
        "deferredRevenueNonCurrent": 0,
        "deferredTaxLiabilitiesNonCurrent": 14980000,
        "otherNonCurrentLiabilities": 0,
        "totalNonCurrentLiabilities": 1376273000,
        "otherLiabilities": 0,
        "capitalLeaseObligations": 1032641000,
        "totalLiabilities": 1636705000,
        "preferredStock": 0,
        "commonStock": 97000,
        "retainedEarnings": 229143000,
        "accumulatedOtherComprehensiveIncomeLoss": 0,
        "othertotalStockholdersEquity": 827451000,
        "totalStockholdersEquity": 1056691000,
        "totalEquity": 1056691000,
        "totalLiabilitiesAndStockholdersEquity": 2693396000,
        "minorityInterest": 0,
        "totalLiabilitiesAndTotalEquity": 2693396000,
        "totalInvestments": 0,
        "totalDebt": 1411435000,
        "netDebt": 1327175000,
        "link": "https://www.sec.gov/Archives/edgar/data/1771515/000177151522000108/0001771515-22-000108-index.htm",
        "finalLink": "https://www.sec.gov/Archives/edgar/data/1771515/000177151522000108/go-20220702.htm"
    },
    {
        "date": "2022-04-02",
        "symbol": "GO",
        "reportedCurrency": "USD",
        "cik": "0001771515",
        "fillingDate": "2022-05-11",
        "acceptedDate": "2022-05-11 16:04:25",
        "calendarYear": "2022",
        "period": "Q1",
        "cashAndCashEquivalents": 137996000,
        "shortTermInvestments": 0,
        "cashAndShortTermInvestments": 137996000,
        "netReceivables": 11582000,
        "inventory": 297394000,
        "otherCurrentAssets": 14160000,
        "totalCurrentAssets": 461132000,
        "propertyPlantEquipmentNet": 1415150000,
        "goodwill": 747943000,
        "intangibleAssets": 53472000,
        "goodwillAndIntangibleAssets": 801415000,
        "longTermInvestments": 0,
        "taxAssets": 0,
        "otherNonCurrentAssets": 29349000,
        "totalNonCurrentAssets": 2245914000,
        "otherAssets": 0,
        "totalAssets": 2707046000,
        "accountPayables": 133203000,
        "shortTermDebt": 49317000,
        "taxPayables": 7450000,
        "deferredRevenue": 0,
        "otherCurrentLiabilities": 52272000,
        "totalCurrentLiabilities": 242242000,
        "longTermDebt": 1427262000,
        "deferredRevenueNonCurrent": 0,
        "deferredTaxLiabilitiesNonCurrent": 13472000,
        "otherNonCurrentLiabilities": 0,
        "totalNonCurrentLiabilities": 1440734000,
        "otherLiabilities": 0,
        "capitalLeaseObligations": 1024553000,
        "totalLiabilities": 1682976000,
        "preferredStock": 0,
        "commonStock": 96000,
        "retainedEarnings": 209049000,
        "accumulatedOtherComprehensiveIncomeLoss": 0,
        "othertotalStockholdersEquity": 814925000,
        "totalStockholdersEquity": 1024070000,
        "totalEquity": 1024070000,
        "totalLiabilitiesAndStockholdersEquity": 2707046000,
        "minorityInterest": 0,
        "totalLiabilitiesAndTotalEquity": 2707046000,
        "totalInvestments": 0,
        "totalDebt": 1476579000,
        "netDebt": 1338583000,
        "link": "https://www.sec.gov/Archives/edgar/data/1771515/000177151522000055/0001771515-22-000055-index.htm",
        "finalLink": "https://www.sec.gov/Archives/edgar/data/1771515/000177151522000055/go-20220402.htm"
    },
    {
        "date": "2021-12-31",
        "symbol": "GO",
        "reportedCurrency": "USD",
        "cik": "0001771515",
        "fillingDate": "2022-03-02",
        "acceptedDate": "2022-03-02 16:04:38",
        "calendarYear": "2021",
        "period": "Q4",
        "cashAndCashEquivalents": 140085000,
        "shortTermInvestments": 0,
        "cashAndShortTermInvestments": 140085000,
        "netReceivables": 10378000,
        "inventory": 275502000,
        "otherCurrentAssets": 16780000,
        "totalCurrentAssets": 442745000,
        "propertyPlantEquipmentNet": 1397539000,
        "goodwill": 747943000,
        "intangibleAssets": 51921000,
        "goodwillAndIntangibleAssets": 799864000,
        "longTermInvestments": 0,
        "taxAssets": 0,
        "otherNonCurrentAssets": 29660000,
        "totalNonCurrentAssets": 2227063000,
        "otherAssets": 0,
        "totalAssets": 2669808000,
        "accountPayables": 122110000,
        "shortTermDebt": 51136000,
        "taxPayables": 7185000,
        "deferredRevenue": 0,
        "otherCurrentLiabilities": 57475000,
        "totalCurrentLiabilities": 237906000,
        "longTermDebt": 1413214000,
        "deferredRevenueNonCurrent": 0,
        "deferredTaxLiabilitiesNonCurrent": 9416000,
        "otherNonCurrentLiabilities": 0,
        "totalNonCurrentLiabilities": 1422630000,
        "otherLiabilities": 0,
        "capitalLeaseObligations": 1012882000,
        "totalLiabilities": 1660536000,
        "preferredStock": 0,
        "commonStock": 96000,
        "retainedEarnings": 197475000,
        "accumulatedOtherComprehensiveIncomeLoss": 0,
        "othertotalStockholdersEquity": 811701000,
        "totalStockholdersEquity": 1009272000,
        "totalEquity": 1009272000,
        "totalLiabilitiesAndStockholdersEquity": 2669808000,
        "minorityInterest": 0,
        "totalLiabilitiesAndTotalEquity": 2669808000,
        "totalInvestments": 0,
        "totalDebt": 1464350000,
        "netDebt": 1324265000,
        "link": "https://www.sec.gov/Archives/edgar/data/1771515/000177151522000011/0001771515-22-000011-index.htm",
        "finalLink": "https://www.sec.gov/Archives/edgar/data/1771515/000177151522000011/go-20220101.htm"
    },
    {
        "date": "2021-10-02",
        "symbol": "GO",
        "reportedCurrency": "USD",
        "cik": "0001771515",
        "fillingDate": "2021-11-10",
        "acceptedDate": "2021-11-10 16:09:44",
        "calendarYear": "2021",
        "period": "Q3",
        "cashAndCashEquivalents": 155976000,
        "shortTermInvestments": 0,
        "cashAndShortTermInvestments": 155976000,
        "netReceivables": 9618000,
        "inventory": 245844000,
        "otherCurrentAssets": 18967000,
        "totalCurrentAssets": 430405000,
        "propertyPlantEquipmentNet": 1360370000,
        "goodwill": 747943000,
        "intangibleAssets": 49242000,
        "goodwillAndIntangibleAssets": 797185000,
        "longTermInvestments": 0,
        "taxAssets": 0,
        "otherNonCurrentAssets": 29708000,
        "totalNonCurrentAssets": 2187263000,
        "otherAssets": 0,
        "totalAssets": 2617668000,
        "accountPayables": 122055000,
        "shortTermDebt": 46013000,
        "taxPayables": 7945000,
        "deferredRevenue": 0,
        "otherCurrentLiabilities": 52448000,
        "totalCurrentLiabilities": 228461000,
        "longTermDebt": 1389620000,
        "deferredRevenueNonCurrent": 0,
        "deferredTaxLiabilitiesNonCurrent": 5556000,
        "otherNonCurrentLiabilities": 0,
        "totalNonCurrentLiabilities": 1395176000,
        "otherLiabilities": 0,
        "capitalLeaseObligations": 984773000,
        "totalLiabilities": 1623637000,
        "preferredStock": 0,
        "commonStock": 96000,
        "retainedEarnings": 190836000,
        "accumulatedOtherComprehensiveIncomeLoss": 0,
        "othertotalStockholdersEquity": 803099000,
        "totalStockholdersEquity": 994031000,
        "totalEquity": 994031000,
        "totalLiabilitiesAndStockholdersEquity": 2617668000,
        "minorityInterest": 0,
        "totalLiabilitiesAndTotalEquity": 2617668000,
        "totalInvestments": 0,
        "totalDebt": 1435633000,
        "netDebt": 1279657000,
        "link": "https://www.sec.gov/Archives/edgar/data/1771515/000177151521000088/0001771515-21-000088-index.htm",
        "finalLink": "https://www.sec.gov/Archives/edgar/data/1771515/000177151521000088/go-20211002.htm"
    },
    {
        "date": "2021-07-03",
        "symbol": "GO",
        "reportedCurrency": "USD",
        "cik": "0001771515",
        "fillingDate": "2021-08-11",
        "acceptedDate": "2021-08-11 16:05:40",
        "calendarYear": "2021",
        "period": "Q2",
        "cashAndCashEquivalents": 126623000,
        "shortTermInvestments": 0,
        "cashAndShortTermInvestments": 126623000,
        "netReceivables": 9350000,
        "inventory": 248172000,
        "otherCurrentAssets": 17845000,
        "totalCurrentAssets": 401990000,
        "propertyPlantEquipmentNet": 1337972000,
        "goodwill": 747943000,
        "intangibleAssets": 48806000,
        "goodwillAndIntangibleAssets": 796749000,
        "longTermInvestments": 0,
        "taxAssets": 0,
        "otherNonCurrentAssets": 29041000,
        "totalNonCurrentAssets": 2163762000,
        "otherAssets": 0,
        "totalAssets": 2565752000,
        "accountPayables": 112062000,
        "shortTermDebt": 44813000,
        "taxPayables": 6805000,
        "deferredRevenue": 0,
        "otherCurrentLiabilities": 50213000,
        "totalCurrentLiabilities": 213893000,
        "longTermDebt": 1376938000,
        "deferredRevenueNonCurrent": 0,
        "deferredTaxLiabilitiesNonCurrent": 1038000,
        "otherNonCurrentLiabilities": 0,
        "totalNonCurrentLiabilities": 1377976000,
        "otherLiabilities": 0,
        "capitalLeaseObligations": 971449000,
        "totalLiabilities": 1591869000,
        "preferredStock": 0,
        "commonStock": 96000,
        "retainedEarnings": 173697000,
        "accumulatedOtherComprehensiveIncomeLoss": 0,
        "othertotalStockholdersEquity": 800090000,
        "totalStockholdersEquity": 973883000,
        "totalEquity": 973883000,
        "totalLiabilitiesAndStockholdersEquity": 2565752000,
        "minorityInterest": 0,
        "totalLiabilitiesAndTotalEquity": 2565752000,
        "totalInvestments": 0,
        "totalDebt": 1421751000,
        "netDebt": 1295128000,
        "link": "https://www.sec.gov/Archives/edgar/data/1771515/000177151521000064/0001771515-21-000064-index.htm",
        "finalLink": "https://www.sec.gov/Archives/edgar/data/1771515/000177151521000064/go-20210703.htm"
    },
    {
        "date": "2021-04-03",
        "symbol": "GO",
        "reportedCurrency": "USD",
        "cik": "0001771515",
        "fillingDate": "2021-05-12",
        "acceptedDate": "2021-05-12 16:06:57",
        "calendarYear": "2021",
        "period": "Q1",
        "cashAndCashEquivalents": 95292000,
        "shortTermInvestments": 0,
        "cashAndShortTermInvestments": 95292000,
        "netReceivables": 8570000,
        "inventory": 243270000,
        "otherCurrentAssets": 17519000,
        "totalCurrentAssets": 364651000,
        "propertyPlantEquipmentNet": 1307967000,
        "goodwill": 747943000,
        "intangibleAssets": 47765000,
        "goodwillAndIntangibleAssets": 795708000,
        "longTermInvestments": 0,
        "taxAssets": 2500000,
        "otherNonCurrentAssets": 27911000,
        "totalNonCurrentAssets": 2134086000,
        "otherAssets": 0,
        "totalAssets": 2498737000,
        "accountPayables": 109841000,
        "shortTermDebt": 35382000,
        "taxPayables": 6353000,
        "deferredRevenue": 0,
        "otherCurrentLiabilities": 45478000,
        "totalCurrentLiabilities": 197054000,
        "longTermDebt": 1353597000,
        "deferredRevenueNonCurrent": 0,
        "deferredTaxLiabilitiesNonCurrent": 0,
        "otherNonCurrentLiabilities": 0,
        "totalNonCurrentLiabilities": 1353597000,
        "otherLiabilities": 0,
        "capitalLeaseObligations": 939236000,
        "totalLiabilities": 1550651000,
        "preferredStock": 0,
        "commonStock": 96000,
        "retainedEarnings": 154057000,
        "accumulatedOtherComprehensiveIncomeLoss": 0,
        "othertotalStockholdersEquity": 793933000,
        "totalStockholdersEquity": 948086000,
        "totalEquity": 948086000,
        "totalLiabilitiesAndStockholdersEquity": 2498737000,
        "minorityInterest": 0,
        "totalLiabilitiesAndTotalEquity": 2498737000,
        "totalInvestments": 0,
        "totalDebt": 1388979000,
        "netDebt": 1293687000,
        "link": "https://www.sec.gov/Archives/edgar/data/1771515/000177151521000042/0001771515-21-000042-index.htm",
        "finalLink": "https://www.sec.gov/Archives/edgar/data/1771515/000177151521000042/go-20210403.htm"
    },
    {
        "date": "2020-12-31",
        "symbol": "GO",
        "reportedCurrency": "USD",
        "cik": "0001771515",
        "fillingDate": "2021-03-02",
        "acceptedDate": "2021-03-02 17:01:07",
        "calendarYear": "2020",
        "period": "Q4",
        "cashAndCashEquivalents": 105326000,
        "shortTermInvestments": 0,
        "cashAndShortTermInvestments": 105326000,
        "netReceivables": 11393000,
        "inventory": 245157000,
        "otherCurrentAssets": 20081000,
        "totalCurrentAssets": 381957000,
        "propertyPlantEquipmentNet": 1269049000,
        "goodwill": 747943000,
        "intangibleAssets": 48226000,
        "goodwillAndIntangibleAssets": 796169000,
        "longTermInvestments": 0,
        "taxAssets": 3529000,
        "otherNonCurrentAssets": 34920000,
        "totalNonCurrentAssets": 2103667000,
        "otherAssets": 0,
        "totalAssets": 2485624000,
        "accountPayables": 114278000,
        "shortTermDebt": 48675000,
        "taxPayables": 7547000,
        "deferredRevenue": 0,
        "otherCurrentLiabilities": 62146000,
        "totalCurrentLiabilities": 232646000,
        "longTermDebt": 1330671000,
        "deferredRevenueNonCurrent": 0,
        "deferredTaxLiabilitiesNonCurrent": 0,
        "otherNonCurrentLiabilities": 0,
        "totalNonCurrentLiabilities": 1330671000,
        "otherLiabilities": 0,
        "capitalLeaseObligations": 930113000,
        "totalLiabilities": 1563317000,
        "preferredStock": 0,
        "commonStock": 95000,
        "retainedEarnings": 135165000,
        "accumulatedOtherComprehensiveIncomeLoss": 0,
        "othertotalStockholdersEquity": 787047000,
        "totalStockholdersEquity": 922307000,
        "totalEquity": 922307000,
        "totalLiabilitiesAndStockholdersEquity": 2485624000,
        "minorityInterest": 0,
        "totalLiabilitiesAndTotalEquity": 2485624000,
        "totalInvestments": 0,
        "totalDebt": 1379346000,
        "netDebt": 1274020000,
        "link": "https://www.sec.gov/Archives/edgar/data/1771515/000177151521000009/0001771515-21-000009-index.htm",
        "finalLink": "https://www.sec.gov/Archives/edgar/data/1771515/000177151521000009/go-20210102.htm"
    },
    {
        "date": "2020-09-26",
        "symbol": "GO",
        "reportedCurrency": "USD",
        "cik": "0001771515",
        "fillingDate": "2020-11-10",
        "acceptedDate": "2020-11-10 16:44:38",
        "calendarYear": "2020",
        "period": "Q3",
        "cashAndCashEquivalents": 59082000,
        "shortTermInvestments": 0,
        "cashAndShortTermInvestments": 59082000,
        "netReceivables": 11846000,
        "inventory": 252777000,
        "otherCurrentAssets": 20958000,
        "totalCurrentAssets": 344663000,
        "propertyPlantEquipmentNet": 1218386000,
        "goodwill": 747943000,
        "intangibleAssets": 46747000,
        "goodwillAndIntangibleAssets": 794690000,
        "longTermInvestments": 0,
        "taxAssets": 2976000,
        "otherNonCurrentAssets": 33551000,
        "totalNonCurrentAssets": 2049603000,
        "otherAssets": 0,
        "totalAssets": 2394266000,
        "accountPayables": 90191000,
        "shortTermDebt": 45861000,
        "taxPayables": 4973000,
        "deferredRevenue": 0,
        "otherCurrentLiabilities": 54953000,
        "totalCurrentLiabilities": 195978000,
        "longTermDebt": 1309462000,
        "deferredRevenueNonCurrent": 0,
        "deferredTaxLiabilitiesNonCurrent": 0,
        "otherNonCurrentLiabilities": 0,
        "totalNonCurrentLiabilities": 1309462000,
        "otherLiabilities": 0,
        "capitalLeaseObligations": 906642000,
        "totalLiabilities": 1505440000,
        "preferredStock": 0,
        "commonStock": 94000,
        "retainedEarnings": 110901000,
        "accumulatedOtherComprehensiveIncomeLoss": 0,
        "othertotalStockholdersEquity": 777831000,
        "totalStockholdersEquity": 888826000,
        "totalEquity": 888826000,
        "totalLiabilitiesAndStockholdersEquity": 2394266000,
        "minorityInterest": 0,
        "totalLiabilitiesAndTotalEquity": 2394266000,
        "totalInvestments": 0,
        "totalDebt": 1355323000,
        "netDebt": 1296241000,
        "link": "https://www.sec.gov/Archives/edgar/data/1771515/000177151520000025/0001771515-20-000025-index.htm",
        "finalLink": "https://www.sec.gov/Archives/edgar/data/1771515/000177151520000025/go-20200926.htm"
    },
    {
        "date": "2020-06-27",
        "symbol": "GO",
        "reportedCurrency": "USD",
        "cik": "0001771515",
        "fillingDate": "2020-08-11",
        "acceptedDate": "2020-08-11 16:32:23",
        "calendarYear": "2020",
        "period": "Q2",
        "cashAndCashEquivalents": 79803000,
        "shortTermInvestments": 0,
        "cashAndShortTermInvestments": 79803000,
        "netReceivables": 13243000,
        "inventory": 229273000,
        "otherCurrentAssets": 12514000,
        "totalCurrentAssets": 334833000,
        "propertyPlantEquipmentNet": 1162300000,
        "goodwill": 747943000,
        "intangibleAssets": 46966000,
        "goodwillAndIntangibleAssets": 794909000,
        "longTermInvestments": 0,
        "taxAssets": 0,
        "otherNonCurrentAssets": 32251000,
        "totalNonCurrentAssets": 1989460000,
        "otherAssets": 0,
        "totalAssets": 2324293000,
        "accountPayables": 104704000,
        "shortTermDebt": 43495000,
        "taxPayables": 10543000,
        "deferredRevenue": 0,
        "otherCurrentLiabilities": 49166000,
        "totalCurrentLiabilities": 207908000,
        "longTermDebt": 1271748000,
        "deferredRevenueNonCurrent": 0,
        "deferredTaxLiabilitiesNonCurrent": 11236000,
        "otherNonCurrentLiabilities": 0,
        "totalNonCurrentLiabilities": 1282984000,
        "otherLiabilities": 0,
        "capitalLeaseObligations": 867083000,
        "totalLiabilities": 1490892000,
        "preferredStock": 0,
        "commonStock": 91000,
        "retainedEarnings": 70427000,
        "accumulatedOtherComprehensiveIncomeLoss": 0,
        "othertotalStockholdersEquity": 762883000,
        "totalStockholdersEquity": 833401000,
        "totalEquity": 833401000,
        "totalLiabilitiesAndStockholdersEquity": 2324293000,
        "minorityInterest": 0,
        "totalLiabilitiesAndTotalEquity": 2324293000,
        "totalInvestments": 0,
        "totalDebt": 1315243000,
        "netDebt": 1235440000,
        "link": "https://www.sec.gov/Archives/edgar/data/1771515/000177151520000018/0001771515-20-000018-index.htm",
        "finalLink": "https://www.sec.gov/Archives/edgar/data/1771515/000177151520000018/go-20200627.htm"
    },
    {
        "date": "2020-03-28",
        "symbol": "GO",
        "reportedCurrency": "USD",
        "cik": "0001771515",
        "fillingDate": "2020-05-12",
        "acceptedDate": "2020-05-12 16:27:01",
        "calendarYear": "2020",
        "period": "Q1",
        "cashAndCashEquivalents": 160936000,
        "shortTermInvestments": 0,
        "cashAndShortTermInvestments": 160936000,
        "netReceivables": 11206000,
        "inventory": 188346000,
        "otherCurrentAssets": 12606000,
        "totalCurrentAssets": 373094000,
        "propertyPlantEquipmentNet": 1120873000,
        "goodwill": 747943000,
        "intangibleAssets": 47526000,
        "goodwillAndIntangibleAssets": 795469000,
        "longTermInvestments": 0,
        "taxAssets": 0,
        "otherNonCurrentAssets": 29661000,
        "totalNonCurrentAssets": 1946003000,
        "otherAssets": 0,
        "totalAssets": 2319097000,
        "accountPayables": 101066000,
        "shortTermDebt": 41460000,
        "taxPayables": 5363000,
        "deferredRevenue": 0,
        "otherCurrentLiabilities": 44601000,
        "totalCurrentLiabilities": 192490000,
        "longTermDebt": 1327761000,
        "deferredRevenueNonCurrent": 0,
        "deferredTaxLiabilitiesNonCurrent": 14218000,
        "otherNonCurrentLiabilities": 0,
        "totalNonCurrentLiabilities": 1341979000,
        "otherLiabilities": 0,
        "capitalLeaseObligations": 831555000,
        "totalLiabilities": 1534469000,
        "preferredStock": 0,
        "commonStock": 90000,
        "retainedEarnings": 41094000,
        "accumulatedOtherComprehensiveIncomeLoss": 0,
        "othertotalStockholdersEquity": 743444000,
        "totalStockholdersEquity": 784628000,
        "totalEquity": 784628000,
        "totalLiabilitiesAndStockholdersEquity": 2319097000,
        "minorityInterest": 0,
        "totalLiabilitiesAndTotalEquity": 2319097000,
        "totalInvestments": 0,
        "totalDebt": 1369221000,
        "netDebt": 1208285000,
        "link": "https://www.sec.gov/Archives/edgar/data/1771515/000177151520000011/0001771515-20-000011-index.htm",
        "finalLink": "https://www.sec.gov/Archives/edgar/data/1771515/000177151520000011/go-20200328.htm"
    },
    {
        "date": "2019-12-31",
        "symbol": "GO",
        "reportedCurrency": "USD",
        "cik": "0001771515",
        "fillingDate": "2020-03-25",
        "acceptedDate": "2020-03-25 16:53:22",
        "calendarYear": "2019",
        "period": "Q4",
        "cashAndCashEquivalents": 28101000,
        "shortTermInvestments": 0,
        "cashAndShortTermInvestments": 28101000,
        "netReceivables": 9852000,
        "inventory": 219420000,
        "otherCurrentAssets": 13453000,
        "totalCurrentAssets": 270826000,
        "propertyPlantEquipmentNet": 1090941000,
        "goodwill": 747943000,
        "intangibleAssets": 47792000,
        "goodwillAndIntangibleAssets": 795735000,
        "longTermInvestments": 0,
        "taxAssets": 0,
        "otherNonCurrentAssets": 28027000,
        "totalNonCurrentAssets": 1914703000,
        "otherAssets": 0,
        "totalAssets": 2185529000,
        "accountPayables": 119217000,
        "shortTermDebt": 38491000,
        "taxPayables": 4641000,
        "deferredRevenue": 0,
        "otherCurrentLiabilities": 46278000,
        "totalCurrentLiabilities": 208627000,
        "longTermDebt": 1215498000,
        "deferredRevenueNonCurrent": 0,
        "deferredTaxLiabilitiesNonCurrent": 16020000,
        "otherNonCurrentLiabilities": 0,
        "totalNonCurrentLiabilities": 1231518000,
        "otherLiabilities": 0,
        "capitalLeaseObligations": 806000000,
        "totalLiabilities": 1440145000,
        "preferredStock": 0,
        "commonStock": 89000,
        "retainedEarnings": 28013000,
        "accumulatedOtherComprehensiveIncomeLoss": 0,
        "othertotalStockholdersEquity": 717282000,
        "totalStockholdersEquity": 745384000,
        "totalEquity": 745384000,
        "totalLiabilitiesAndStockholdersEquity": 2185529000,
        "minorityInterest": 0,
        "totalLiabilitiesAndTotalEquity": 2185529000,
        "totalInvestments": 0,
        "totalDebt": 1253989000,
        "netDebt": 1225888000,
        "link": "https://www.sec.gov/Archives/edgar/data/1771515/000177151520000005/0001771515-20-000005-index.htm",
        "finalLink": "https://www.sec.gov/Archives/edgar/data/1771515/000177151520000005/go-20191228.htm"
    },
    {
        "date": "2019-09-28",
        "symbol": "GO",
        "reportedCurrency": "USD",
        "cik": "0001771515",
        "fillingDate": "2019-11-12",
        "acceptedDate": "2019-11-12 08:08:37",
        "calendarYear": "2019",
        "period": "Q3",
        "cashAndCashEquivalents": 44020000,
        "shortTermInvestments": 0,
        "cashAndShortTermInvestments": 44020000,
        "netReceivables": 9710000,
        "inventory": 206418000,
        "otherCurrentAssets": 17843000,
        "totalCurrentAssets": 277991000,
        "propertyPlantEquipmentNet": 1020441000,
        "goodwill": 747943000,
        "intangibleAssets": 64091000,
        "goodwillAndIntangibleAssets": 812034000,
        "longTermInvestments": 0,
        "taxAssets": 0,
        "otherNonCurrentAssets": 24380000,
        "totalNonCurrentAssets": 1856855000,
        "otherAssets": 0,
        "totalAssets": 2134846000,
        "accountPayables": 116486000,
        "shortTermDebt": 39313000,
        "taxPayables": 4141000,
        "deferredRevenue": 0,
        "otherCurrentLiabilities": 46291000,
        "totalCurrentLiabilities": 206231000,
        "longTermDebt": 1181813000,
        "deferredRevenueNonCurrent": 0,
        "deferredTaxLiabilitiesNonCurrent": 15924000,
        "otherNonCurrentLiabilities": 0,
        "totalNonCurrentLiabilities": 1197737000,
        "otherLiabilities": 0,
        "capitalLeaseObligations": 758608000,
        "totalLiabilities": 1403968000,
        "preferredStock": 0,
        "commonStock": 88000,
        "retainedEarnings": 17803000,
        "accumulatedOtherComprehensiveIncomeLoss": 0,
        "othertotalStockholdersEquity": 712987000,
        "totalStockholdersEquity": 730878000,
        "totalEquity": 730878000,
        "totalLiabilitiesAndStockholdersEquity": 2134846000,
        "minorityInterest": 0,
        "totalLiabilitiesAndTotalEquity": 2134846000,
        "totalInvestments": 0,
        "totalDebt": 1221126000,
        "netDebt": 1177106000,
        "link": "https://www.sec.gov/Archives/edgar/data/1771515/000177151519000011/0001771515-19-000011-index.htm",
        "finalLink": "https://www.sec.gov/Archives/edgar/data/1771515/000177151519000011/go-20190928.htm"
    },
    {
        "date": "2019-06-29",
        "symbol": "GO",
        "reportedCurrency": "USD",
        "cik": "0001771515",
        "fillingDate": "2019-08-13",
        "acceptedDate": "2019-08-13 16:49:39",
        "calendarYear": "2019",
        "period": "Q2",
        "cashAndCashEquivalents": 18677000,
        "shortTermInvestments": 0,
        "cashAndShortTermInvestments": 18677000,
        "netReceivables": 8503000,
        "inventory": 202715000,
        "otherCurrentAssets": 17724000,
        "totalCurrentAssets": 247619000,
        "propertyPlantEquipmentNet": 998663000,
        "goodwill": 747943000,
        "intangibleAssets": 65400000,
        "goodwillAndIntangibleAssets": 813343000,
        "longTermInvestments": 0,
        "taxAssets": 0,
        "otherNonCurrentAssets": 21973000,
        "totalNonCurrentAssets": 1833979000,
        "otherAssets": 0,
        "totalAssets": 2081598000,
        "accountPayables": 102482000,
        "shortTermDebt": 36416000,
        "taxPayables": 2210000,
        "deferredRevenue": 0,
        "otherCurrentLiabilities": 35162000,
        "totalCurrentLiabilities": 176270000,
        "longTermDebt": 1176292000,
        "deferredRevenueNonCurrent": 0,
        "deferredTaxLiabilitiesNonCurrent": 12348000,
        "otherNonCurrentLiabilities": 0,
        "totalNonCurrentLiabilities": 1188640000,
        "otherLiabilities": 0,
        "capitalLeaseObligations": 750322000,
        "totalLiabilities": 1364910000,
        "preferredStock": 0,
        "commonStock": 88000,
        "retainedEarnings": 5400000,
        "accumulatedOtherComprehensiveIncomeLoss": 0,
        "othertotalStockholdersEquity": 711200000,
        "totalStockholdersEquity": 716688000,
        "totalEquity": 716688000,
        "totalLiabilitiesAndStockholdersEquity": 2081598000,
        "minorityInterest": 0,
        "totalLiabilitiesAndTotalEquity": 2081598000,
        "totalInvestments": 0,
        "totalDebt": 1212708000,
        "netDebt": 1194031000,
        "link": "https://www.sec.gov/Archives/edgar/data/1771515/000177151519000005/0001771515-19-000005-index.htm",
        "finalLink": "https://www.sec.gov/Archives/edgar/data/1771515/000177151519000005/groceryoutlet2019q210-q.htm"
    },
    {
        "date": "2019-03-31",
        "symbol": "GO",
        "reportedCurrency": "USD",
        "cik": "0001771515",
        "fillingDate": "2019-03-31",
        "acceptedDate": "2019-03-30 20:00:00",
        "calendarYear": "2019",
        "period": "Q1",
        "cashAndCashEquivalents": 19596000,
        "shortTermInvestments": 0,
        "cashAndShortTermInvestments": 19596000,
        "netReceivables": 8774000,
        "inventory": 212520000,
        "otherCurrentAssets": 15724000,
        "totalCurrentAssets": 256614000,
        "propertyPlantEquipmentNet": 968017000,
        "goodwill": 747943000,
        "intangibleAssets": 66991000,
        "goodwillAndIntangibleAssets": 814934000,
        "longTermInvestments": 0,
        "taxAssets": 0,
        "otherNonCurrentAssets": 20347000,
        "totalNonCurrentAssets": 1803298000,
        "otherAssets": 0,
        "totalAssets": 2059912000,
        "accountPayables": 112492000,
        "shortTermDebt": 39146000,
        "taxPayables": 3096000,
        "deferredRevenue": 0,
        "otherCurrentLiabilities": 38880000,
        "totalCurrentLiabilities": 193614000,
        "longTermDebt": 1545876000,
        "deferredRevenueNonCurrent": 0,
        "deferredTaxLiabilitiesNonCurrent": 16571000,
        "otherNonCurrentLiabilities": 0,
        "totalNonCurrentLiabilities": 1562447000,
        "otherLiabilities": 0,
        "capitalLeaseObligations": 730366000,
        "totalLiabilities": 1756061000,
        "preferredStock": 0,
        "commonStock": 68000,
        "retainedEarnings": 16115000,
        "accumulatedOtherComprehensiveIncomeLoss": 0,
        "othertotalStockholdersEquity": 287668000,
        "totalStockholdersEquity": 303851000,
        "totalEquity": 303851000,
        "totalLiabilitiesAndStockholdersEquity": 2059912000,
        "minorityInterest": 0,
        "totalLiabilitiesAndTotalEquity": 2059912000,
        "totalInvestments": 0,
        "totalDebt": 1585022000,
        "netDebt": 1565426000,
        "link": "",
        "finalLink": ""
    },
    {
        "date": "2018-12-31",
        "symbol": "GO",
        "reportedCurrency": "USD",
        "cik": "0001771515",
        "fillingDate": "2018-12-31",
        "acceptedDate": "2018-12-30 19:00:00",
        "calendarYear": "2018",
        "period": "Q4",
        "cashAndCashEquivalents": 21063000,
        "shortTermInvestments": 0,
        "cashAndShortTermInvestments": 21063000,
        "netReceivables": 7125000,
        "inventory": 198304000,
        "otherCurrentAssets": 13880000,
        "totalCurrentAssets": 240372000,
        "propertyPlantEquipmentNet": 304032000,
        "goodwill": 747943000,
        "intangibleAssets": 68824000,
        "goodwillAndIntangibleAssets": 816767000,
        "longTermInvestments": 0,
        "taxAssets": 0,
        "otherNonCurrentAssets": 15691000,
        "totalNonCurrentAssets": 1136490000,
        "otherAssets": 0,
        "totalAssets": 1376862000,
        "accountPayables": 98123000,
        "shortTermDebt": 7349000,
        "taxPayables": 3463000,
        "deferredRevenue": 0,
        "otherCurrentLiabilities": 41989000,
        "totalCurrentLiabilities": 150924000,
        "longTermDebt": 850019000,
        "deferredRevenueNonCurrent": 0,
        "deferredTaxLiabilitiesNonCurrent": 15135000,
        "otherNonCurrentLiabilities": 60833000,
        "totalNonCurrentLiabilities": 925987000,
        "otherLiabilities": 0,
        "capitalLeaseObligations": 0,
        "totalLiabilities": 1076911000,
        "preferredStock": 0,
        "commonStock": 68000,
        "retainedEarnings": 12426000,
        "accumulatedOtherComprehensiveIncomeLoss": 0,
        "othertotalStockholdersEquity": 287457000,
        "totalStockholdersEquity": 299951000,
        "totalEquity": 299951000,
        "totalLiabilitiesAndStockholdersEquity": 1376862000,
        "minorityInterest": 0,
        "totalLiabilitiesAndTotalEquity": 1376862000,
        "totalInvestments": 0,
        "totalDebt": 857368000,
        "netDebt": 836305000,
        "link": "",
        "finalLink": ""
    }
]