[
    {
        "symbol": "Q",
        "price": 90.31,
        "beta": 0,
        "volAvg": 2456115,
        "mktCap": 18916621050,
        "lastDiv": 0.06,
        "range": "70.5-105.4",
        "changes": 0.81,
        "companyName": "Qnity Electronics, Inc.",
        "currency": "USD",
        "cik": "0002058873",
        "isin": "US74743L1008",
        "cusip": "74743L100",
        "exchange": "New York Stock Exchange",
        "exchangeShortName": "NYSE",
        "industry": "Semiconductors",
        "website": "http://www.qnityelectronics.com",
        "description": "Qnity Electronics, Inc. focuses on the provision of electronic solutions and materials used in semiconductor chip manufacturing and advanced electronic materials. The company was formerly known as Novus SpinCo 1, Inc. and changed its name to Qnity Electronics, Inc. in April 2025. Qnity Electronics, Inc. is based in Wilmington, Delaware.",
        "ceo": "Jon D. Kemp",
        "sector": "Technology",
        "country": "US",
        "fullTimeEmployees": null,
        "phone": "302-294-4651",
        "address": "Building 735",
        "city": "Wilmington",
        "state": "DE",
        "zip": "19805",
        "dcfDiff": 11.56864,
        "dcf": 78.74375647608652,
        "image": "https://images.financialmodelingprep.com/symbol/Q.png",
        "ipoDate": "2025-10-27",
        "defaultImage": true,
        "isEtf": false,
        "isActivelyTrading": true,
        "isAdr": false,
        "isFund": false
    }
]